auto_release_snake/__init__.py
auto_release_snake/cli.py
auto_release_snake-0.1.2.dist-info/LICENSE
auto_release_snake-0.1.2.dist-info/METADATA
auto_release_snake-0.1.2.dist-info/WHEEL
auto_release_snake-0.1.2.dist-info/entry_points.txt
auto_release_snake-0.1.2.dist-info/RECORD
